cellarium/ml/__init__.py
cellarium/ml/cli.py
cellarium/ml/py.typed
cellarium/ml/callbacks/__init__.py
cellarium/ml/callbacks/prediction_writer.py
cellarium/ml/callbacks/variance_monitor.py
cellarium/ml/core/__init__.py
cellarium/ml/core/datamodule.py
cellarium/ml/core/module.py
cellarium/ml/core/pipeline.py
cellarium/ml/data/__init__.py
cellarium/ml/data/dadc_dataset.py
cellarium/ml/data/distributed_anndata.py
cellarium/ml/data/fileio.py
cellarium/ml/data/schema.py
cellarium/ml/distributed/__init__.py
cellarium/ml/distributed/gather.py
cellarium/ml/distributions/__init__.py
cellarium/ml/distributions/negative_binomial.py
cellarium/ml/lr_schedulers/__init__.py
cellarium/ml/lr_schedulers/linear_lr.py
cellarium/ml/models/__init__.py
cellarium/ml/models/geneformer.py
cellarium/ml/models/incremental_pca.py
cellarium/ml/models/logistic_regression.py
cellarium/ml/models/model.py
cellarium/ml/models/mu_linear.py
cellarium/ml/models/onepass_mean_var_std.py
cellarium/ml/models/probabilistic_pca.py
cellarium/ml/models/tdigest.py
cellarium/ml/preprocessing/__init__.py
cellarium/ml/preprocessing/highly_variable_genes.py
cellarium/ml/transforms/__init__.py
cellarium/ml/transforms/divide_by_scale.py
cellarium/ml/transforms/filter.py
cellarium/ml/transforms/log1p.py
cellarium/ml/transforms/normalize_total.py
cellarium/ml/transforms/z_score.py
cellarium/ml/utilities/__init__.py
cellarium/ml/utilities/core.py
cellarium/ml/utilities/data.py
cellarium/ml/utilities/testing.py
cellarium_ml-0.0.7.dist-info/LICENSE.md
cellarium_ml-0.0.7.dist-info/METADATA
cellarium_ml-0.0.7.dist-info/WHEEL
cellarium_ml-0.0.7.dist-info/entry_points.txt
cellarium_ml-0.0.7.dist-info/top_level.txt
cellarium_ml-0.0.7.dist-info/RECORD
