Metadata-Version: 2.1
Name: cellarium-ml
Version: 0.0.7
Summary: Machine learning library for single-cell data analysis
Author-email: Yerdos Ordabayev <yordabay@broadinstitute.org>, Mehrtash Babadi <mehrtash@broadinstitute.org>
License: Copyright (c) 2023, Broad Institute
Project-URL: Homepage, https://cellarium-ai.github.io/cellarium-ml
Project-URL: Source Code, https://github.com/cellarium-ai/cellarium-ml
Project-URL: Bug Tracker, https://github.com/cellarium-ai/cellarium-ml/issues
Project-URL: Discussion Forum, https://github.com/cellarium-ai/cellarium-ml/discussions
Classifier: Intended Audience :: Developers
Classifier: Intended Audience :: Science/Research
Classifier: License :: OSI Approved :: BSD License
Classifier: Operating System :: OS Independent
Classifier: Programming Language :: Python :: 3
Requires-Python: >=3.10
License-File: LICENSE.md
Requires-Dist: anndata
Requires-Dist: boltons
Requires-Dist: braceexpand
Requires-Dist: crick >=0.0.4
Requires-Dist: google-cloud-storage
Requires-Dist: jsonargparse[signatures] ==4.27.7
Requires-Dist: lightning >=2.2.0
Requires-Dist: pyro-ppl
Requires-Dist: pytest
Requires-Dist: torch >=2.2.0
Requires-Dist: transformers
Provides-Extra: dev
Requires-Dist: cellarium-ml[docs,lint,mypy,test] ; extra == 'dev'
Provides-Extra: docs
Requires-Dist: nbsphinx ; extra == 'docs'
Requires-Dist: Pillow ; extra == 'docs'
Requires-Dist: seaborn >=0.13.0 ; extra == 'docs'
Requires-Dist: sphinx ; extra == 'docs'
Requires-Dist: sphinx-rtd-theme ; extra == 'docs'
Requires-Dist: sphinx-copybutton ; extra == 'docs'
Provides-Extra: lint
Requires-Dist: ruff ; extra == 'lint'
Provides-Extra: mypy
Requires-Dist: mypy ; extra == 'mypy'
Requires-Dist: types-PyYAML ; extra == 'mypy'
Provides-Extra: test
Requires-Dist: pytest-xdist ; extra == 'test'
Requires-Dist: tensorboard ; extra == 'test'
Requires-Dist: torchvision ; extra == 'test'
